fleet_x-0.0.8.dist-info/DESCRIPTION.rst
fleet_x-0.0.8.dist-info/METADATA
fleet_x-0.0.8.dist-info/RECORD
fleet_x-0.0.8.dist-info/WHEEL
fleet_x-0.0.8.dist-info/entry_points.txt
fleet_x-0.0.8.dist-info/metadata.json
fleet_x-0.0.8.dist-info/top_level.txt
fleetx/__init__.py
fleetx/fleetx.py
fleetx/version.py
fleetx/applications/__init__.py
fleetx/applications/model.py
fleetx/applications/trainer.py
fleetx/applications/util.py
fleetx/dataset/__init__.py
fleetx/dataset/bert_dataset.py
fleetx/dataset/ctr_data_generator.py
fleetx/dataset/dali.py
fleetx/dataset/image_dataset.py
fleetx/dataset/img_tool.py
fleetx/dataset/transformer_dataset.py
fleetx/dataset/word2vec_dataset.py
fleetx/utils/__init__.py
fleetx/utils/barrier_client_impl.py
fleetx/utils/barrier_server_impl.py
fleetx/utils/barrier_server_pb2.py
fleetx/utils/barrier_server_pb2_grpc.py
fleetx/utils/downloader.py
fleetx/utils/env.py
fleetx/utils/lr_strategy.py
fleetx/utils/submitter.py
fleetx/utils/test_barrier_client.py
fleetx/utils/test_barrier_server.py
