Metadata-Version: 2.0
Name: fleet-x
Version: 0.0.8
Summary: UNKNOWN
Home-page: https://github.com/PaddlePaddle/Fleet
Author: PaddlePaddle Author
Author-email: paddle-dev@baidu.com
License: Apache 2.0
Keywords: paddlepaddle distributed-training deep-learning
Platform: UNKNOWN
Classifier: Development Status :: 4 - Beta
Classifier: Intended Audience :: Developers
Classifier: Intended Audience :: Education
Classifier: Intended Audience :: Science/Research
Classifier: License :: OSI Approved :: Apache Software License
Classifier: Programming Language :: Python :: 2.7
Classifier: Programming Language :: Python :: 3
Classifier: Programming Language :: Python :: 3.4
Classifier: Programming Language :: Python :: 3.5
Classifier: Programming Language :: Python :: 3.6
Classifier: Topic :: Scientific/Engineering
Classifier: Topic :: Scientific/Engineering :: Mathematics
Classifier: Topic :: Scientific/Engineering :: Artificial Intelligence
Classifier: Topic :: Software Development
Classifier: Topic :: Software Development :: Libraries
Classifier: Topic :: Software Development :: Libraries :: Python Modules
Requires-Dist: numpy (>=1.10.0)
Requires-Dist: grpcio
Requires-Dist: grpcio-tools
